Metadata-Version: 2.1
Name: libnadagclient
Version: 0.0.4
Summary: Client library for the geotechnical database
Home-page: https://github.com/emerald-geomodelling/libnadagclient
Author: Egil Moeller
Author-email: em@emeraldgeo.no
License: UNKNOWN
Platform: UNKNOWN
License-File: LICENSE
